odoo9_addon_stock_batch_picking-9.0.1.0.3-nspkg.pth
odoo_addons/stock_batch_picking/README.rst
odoo_addons/stock_batch_picking/__init__.py
odoo_addons/stock_batch_picking/__openerp__.py
odoo_addons/stock_batch_picking/data/stock_batch_picking_sequence.xml
odoo_addons/stock_batch_picking/i18n/de.po
odoo_addons/stock_batch_picking/i18n/es.po
odoo_addons/stock_batch_picking/i18n/fr.po
odoo_addons/stock_batch_picking/i18n/it.po
odoo_addons/stock_batch_picking/i18n/pt_BR.po
odoo_addons/stock_batch_picking/i18n/sl.po
odoo_addons/stock_batch_picking/i18n/stock_batch_picking.pot
odoo_addons/stock_batch_picking/models/__init__.py
odoo_addons/stock_batch_picking/models/product_product.py
odoo_addons/stock_batch_picking/models/stock_batch_picking.py
odoo_addons/stock_batch_picking/models/stock_picking.py
odoo_addons/stock_batch_picking/models/stock_warehouse.py
odoo_addons/stock_batch_picking/report/__init__.py
odoo_addons/stock_batch_picking/report/batch_aggregation.py
odoo_addons/stock_batch_picking/report/batch_report.py
odoo_addons/stock_batch_picking/report/print_batch.py
odoo_addons/stock_batch_picking/security/ir.model.access.csv
odoo_addons/stock_batch_picking/static/batch_form.png
odoo_addons/stock_batch_picking/static/batch_form_operation.png
odoo_addons/stock_batch_picking/static/batch_wizard.png
odoo_addons/stock_batch_picking/static/stock_picking_list.png
odoo_addons/stock_batch_picking/static/description/icon.png
odoo_addons/stock_batch_picking/tests/__init__.py
odoo_addons/stock_batch_picking/tests/common.py
odoo_addons/stock_batch_picking/tests/test_batch.py
odoo_addons/stock_batch_picking/tests/test_print_batch.py
odoo_addons/stock_batch_picking/views/product_product.xml
odoo_addons/stock_batch_picking/views/report_batch_picking.xml
odoo_addons/stock_batch_picking/views/stock_batch_picking.xml
odoo_addons/stock_batch_picking/views/stock_picking.xml
odoo_addons/stock_batch_picking/views/stock_warehouse.xml
odoo_addons/stock_batch_picking/wizard/__init__.py
odoo9_addon_stock_batch_picking-9.0.1.0.3.dist-info/METADATA
odoo9_addon_stock_batch_picking-9.0.1.0.3.dist-info/WHEEL
odoo9_addon_stock_batch_picking-9.0.1.0.3.dist-info/namespace_packages.txt
odoo9_addon_stock_batch_picking-9.0.1.0.3.dist-info/top_level.txt
odoo9_addon_stock_batch_picking-9.0.1.0.3.dist-info/RECORD
